{"repo": {"name": {"en-US": "My First F-Droid Repo Demo"}, "description": {"en-US": "Dies ist eine Paketquelle für Anwendungen, die für die Benutzung zusammen mit F-Droid gedacht ist. Die darin enthaltenen Anwendungen sind entweder offizielle von den Entwicklern erstellte Binärdateien oder werden von f-droid.org mithilfe des Werkzeugs auf https://gitlab.com/fdroid aus dem Quellcode erstellt."}, "icon": {"en-US": {"name": "/icons/icon.png", "sha256": "c03488b175b395dc272b09c9a2b2541759a83d690e76bc7e4be12775a67656e6", "size": 960}}, "address": "https://raw.githubusercontent.com/s3tupw1zard/fdroid/main/fdroid/repo", "timestamp": 1723182721000}, "packages": {}}